siamo_ragazzi/__main__.py
siamo_ragazzi/fonts/Roboto-Regular.ttf
siamo_ragazzi/fonts/Roboto-Regular.ttf.OFL.txt
siamo_ragazzi-1.1.0.dist-info/METADATA
siamo_ragazzi-1.1.0.dist-info/WHEEL
siamo_ragazzi-1.1.0.dist-info/entry_points.txt
siamo_ragazzi-1.1.0.dist-info/licenses/LICENSE.txt
siamo_ragazzi-1.1.0.dist-info/RECORD
