Metadata-Version: 2.4
Name: siamo_ragazzi
Version: 1.1.0
Summary: Cringe meta-ironic old meme generator
License-Expression: EUPL-1.2
License-File: LICENSE.txt
Keywords: meme,cringe,siamo-ragazzi
Author: Stefano Pigozzi
Author-email: me@steffo.eu
Maintainer: Stefano Pigozzi
Maintainer-email: me@steffo.eu
Requires-Python: >=3.9,<4.0
Classifier: Development Status :: 7 - Inactive
Classifier: Intended Audience :: End Users/Desktop
Classifier: Programming Language :: Python :: 3
Classifier: Programming Language :: Python :: 3.9
Classifier: Programming Language :: Python :: 3.10
Classifier: Programming Language :: Python :: 3.11
Classifier: Programming Language :: Python :: 3.12
Classifier: Programming Language :: Python :: 3.13
Classifier: License :: OSI Approved :: European Union Public Licence 1.2 (EUPL 1.2)
Classifier: Natural Language :: Italian
Classifier: Operating System :: OS Independent
Requires-Dist: Pillow (>=8.3.1,<11.0.0)
Requires-Dist: click (>=8.0.1,<9.0.0)
Project-URL: Documentation, https://forge.steffo.eu/steffo/siamo-ragazzi/wiki
Project-URL: Source, https://forge.steffo.eu/steffo/siamo-ragazzi
